{
  "run_time": "2026-06-10T17:20:35.517688+00:00",
  "decisions": [
    {
      "ticker": "AAPL_US_EQ",
      "yf_symbol": "AAPL",
      "action": "HOLD",
      "confidence": 0,
      "reasoning": "Model returned no decision",
      "was_executed": false,
      "rejection_reason": "Model error or no response",
      "indicators": {
        "symbol": "AAPL",
        "current_price": 292.0799865722656,
        "volume": 1106272,
        "rsi_14": 37.93,
        "macd": -3.1196,
        "macd_signal": -4.0632,
        "macd_histogram": 0.9436,
        "bb_upper": 293.11,
        "bb_middle": 290.86,
        "bb_lower": 288.62,
        "bb_pct": 0.7713,
        "bb_width": 1.5427,
        "ema_9": 291.36,
        "ema_21": 293.47,
        "ema_trend": "bearish",
        "atr_14": 2.112,
        "obv_trend": "rising",
        "price_change_pct": -0.08
      }
    },
    {
      "ticker": "JPM_US_EQ",
      "yf_symbol": "JPM",
      "action": "HOLD",
      "confidence": 0,
      "reasoning": "Model returned no decision",
      "was_executed": false,
      "rejection_reason": "Model error or no response",
      "indicators": {
        "symbol": "JPM",
        "current_price": 312.13848876953125,
        "volume": 189587,
        "rsi_14": 50.3,
        "macd": 0.0386,
        "macd_signal": 0.0925,
        "macd_histogram": -0.0539,
        "bb_upper": 314.81,
        "bb_middle": 312.1,
        "bb_lower": 309.39,
        "bb_pct": 0.5074,
        "bb_width": 1.7356,
        "ema_9": 312.1,
        "ema_21": 312.12,
        "ema_trend": "bearish",
        "atr_14": 1.7865,
        "obv_trend": "rising",
        "price_change_pct": -0.17
      }
    },
    {
      "ticker": "XOM_US_EQ",
      "yf_symbol": "XOM",
      "action": "HOLD",
      "confidence": 0,
      "reasoning": "Model returned no decision",
      "was_executed": false,
      "rejection_reason": "Model error or no response",
      "indicators": {
        "symbol": "XOM",
        "current_price": 152.33999633789062,
        "volume": 472223,
        "rsi_14": 64.49,
        "macd": 0.3467,
        "macd_signal": -0.0496,
        "macd_histogram": 0.3963,
        "bb_upper": 152.42,
        "bb_middle": 149.71,
        "bb_lower": 147.0,
        "bb_pct": 0.9846,
        "bb_width": 3.622,
        "ema_9": 151.08,
        "ema_21": 150.51,
        "ema_trend": "bullish",
        "atr_14": 0.9403,
        "obv_trend": "falling",
        "price_change_pct": 0.44
      }
    },
    {
      "ticker": "JNJ_US_EQ",
      "yf_symbol": "JNJ",
      "action": "HOLD",
      "confidence": 0,
      "reasoning": "Model returned no decision",
      "was_executed": false,
      "rejection_reason": "Model error or no response",
      "indicators": {
        "symbol": "JNJ",
        "current_price": 238.85000610351562,
        "volume": 177342,
        "rsi_14": 65.35,
        "macd": 1.7271,
        "macd_signal": 1.7472,
        "macd_histogram": -0.0201,
        "bb_upper": 241.6,
        "bb_middle": 237.35,
        "bb_lower": 233.1,
        "bb_pct": 0.6765,
        "bb_width": 3.5821,
        "ema_9": 238.76,
        "ema_21": 237.25,
        "ema_trend": "bullish",
        "atr_14": 1.172,
        "obv_trend": "falling",
        "price_change_pct": -0.16
      }
    },
    {
      "ticker": "WMT_US_EQ",
      "yf_symbol": "WMT",
      "action": "HOLD",
      "confidence": 0,
      "reasoning": "Model returned no decision",
      "was_executed": false,
      "rejection_reason": "Model error or no response",
      "indicators": {
        "symbol": "WMT",
        "current_price": 119.5999984741211,
        "volume": 406737,
        "rsi_14": 53.38,
        "macd": 0.0315,
        "macd_signal": -0.0588,
        "macd_histogram": 0.0904,
        "bb_upper": 120.36,
        "bb_middle": 119.22,
        "bb_lower": 118.08,
        "bb_pct": 0.6672,
        "bb_width": 1.9159,
        "ema_9": 119.39,
        "ema_21": 119.31,
        "ema_trend": "bullish",
        "atr_14": 0.7552,
        "obv_trend": "rising",
        "price_change_pct": 0.0
      }
    }
  ]
}