{
  "run_time": "2026-04-28T20:01:56.928469+00:00",
  "decisions": [
    {
      "ticker": "AAPL_US_EQ",
      "yf_symbol": "AAPL",
      "action": "HOLD",
      "confidence": 0,
      "reasoning": "Model returned no decision",
      "was_executed": false,
      "rejection_reason": "Model error or no response",
      "indicators": {
        "symbol": "AAPL",
        "current_price": 270.760009765625,
        "volume": 3115541,
        "rsi_14": 58.85,
        "macd": 0.3248,
        "macd_signal": 0.0837,
        "macd_histogram": 0.2411,
        "bb_upper": 272.55,
        "bb_middle": 269.05,
        "bb_lower": 265.55,
        "bb_pct": 0.744,
        "bb_width": 2.6044,
        "ema_9": 270.14,
        "ema_21": 269.67,
        "ema_trend": "bullish",
        "atr_14": 1.0853,
        "obv_trend": "rising",
        "price_change_pct": 0.2
      }
    },
    {
      "ticker": "JPM_US_EQ",
      "yf_symbol": "JPM",
      "action": "HOLD",
      "confidence": 0,
      "reasoning": "Model returned no decision",
      "was_executed": false,
      "rejection_reason": "Model error or no response",
      "indicators": {
        "symbol": "JPM",
        "current_price": 311.5199890136719,
        "volume": 589489,
        "rsi_14": 48.54,
        "macd": 0.2311,
        "macd_signal": 0.3849,
        "macd_histogram": -0.1539,
        "bb_upper": 313.67,
        "bb_middle": 312.0,
        "bb_lower": 310.32,
        "bb_pct": 0.3575,
        "bb_width": 1.0749,
        "ema_9": 311.9,
        "ema_21": 311.77,
        "ema_trend": "bullish",
        "atr_14": 0.9032,
        "obv_trend": "falling",
        "price_change_pct": -0.03
      }
    },
    {
      "ticker": "XOM_US_EQ",
      "yf_symbol": "XOM",
      "action": "HOLD",
      "confidence": 0,
      "reasoning": "Model returned no decision",
      "was_executed": false,
      "rejection_reason": "Model error or no response",
      "indicators": {
        "symbol": "XOM",
        "current_price": 150.6020050048828,
        "volume": 1957872,
        "rsi_14": 54.48,
        "macd": 0.5228,
        "macd_signal": 0.559,
        "macd_histogram": -0.0362,
        "bb_upper": 152.81,
        "bb_middle": 150.17,
        "bb_lower": 147.53,
        "bb_pct": 0.5822,
        "bb_width": 3.5119,
        "ema_9": 150.8,
        "ema_21": 150.34,
        "ema_trend": "bullish",
        "atr_14": 0.7162,
        "obv_trend": "falling",
        "price_change_pct": -0.13
      }
    },
    {
      "ticker": "JNJ_US_EQ",
      "yf_symbol": "JNJ",
      "action": "HOLD",
      "confidence": 0,
      "reasoning": "Model returned no decision",
      "was_executed": false,
      "rejection_reason": "Model error or no response",
      "indicators": {
        "symbol": "JNJ",
        "current_price": 227.77999877929688,
        "volume": 767751,
        "rsi_14": 52.07,
        "macd": 0.0452,
        "macd_signal": 0.082,
        "macd_histogram": -0.0368,
        "bb_upper": 230.72,
        "bb_middle": 227.31,
        "bb_lower": 223.9,
        "bb_pct": 0.5687,
        "bb_width": 2.9995,
        "ema_9": 227.53,
        "ema_21": 227.5,
        "ema_trend": "bullish",
        "atr_14": 0.9808,
        "obv_trend": "rising",
        "price_change_pct": 0.1
      }
    },
    {
      "ticker": "WMT_US_EQ",
      "yf_symbol": "WMT",
      "action": "HOLD",
      "confidence": 0,
      "reasoning": "Model returned no decision",
      "was_executed": false,
      "rejection_reason": "Model error or no response",
      "indicators": {
        "symbol": "WMT",
        "current_price": 127.58999633789062,
        "volume": 1584018,
        "rsi_14": 42.96,
        "macd": -0.5326,
        "macd_signal": -0.5456,
        "macd_histogram": 0.013,
        "bb_upper": 128.74,
        "bb_middle": 127.79,
        "bb_lower": 126.84,
        "bb_pct": 0.3967,
        "bb_width": 1.4867,
        "ema_9": 127.48,
        "ema_21": 127.93,
        "ema_trend": "bearish",
        "atr_14": 0.5953,
        "obv_trend": "falling",
        "price_change_pct": 0.43
      }
    }
  ]
}