{
  "run_time": "2026-06-12T19:05:04.038711+00:00",
  "decisions": [
    {
      "ticker": "AAPL_US_EQ",
      "yf_symbol": "AAPL",
      "action": "HOLD",
      "confidence": 0,
      "reasoning": "Model returned no decision",
      "was_executed": false,
      "rejection_reason": "Model error or no response",
      "indicators": {
        "symbol": "AAPL",
        "current_price": 290.875,
        "volume": 265550,
        "rsi_14": 42.72,
        "macd": -0.8911,
        "macd_signal": -0.7182,
        "macd_histogram": -0.1729,
        "bb_upper": 296.81,
        "bb_middle": 292.74,
        "bb_lower": 288.66,
        "bb_pct": 0.2714,
        "bb_width": 2.7849,
        "ema_9": 291.13,
        "ema_21": 291.98,
        "ema_trend": "bearish",
        "atr_14": 1.666,
        "obv_trend": "rising",
        "price_change_pct": 0.14
      }
    },
    {
      "ticker": "JPM_US_EQ",
      "yf_symbol": "JPM",
      "action": "HOLD",
      "confidence": 0,
      "reasoning": "Model returned no decision",
      "was_executed": false,
      "rejection_reason": "Model error or no response",
      "indicators": {
        "symbol": "JPM",
        "current_price": 320.81500244140625,
        "volume": 55242,
        "rsi_14": 71.43,
        "macd": 2.2015,
        "macd_signal": 1.9673,
        "macd_histogram": 0.2342,
        "bb_upper": 324.24,
        "bb_middle": 316.82,
        "bb_lower": 309.4,
        "bb_pct": 0.7692,
        "bb_width": 4.6828,
        "ema_9": 319.49,
        "ema_21": 317.36,
        "ema_trend": "bullish",
        "atr_14": 1.5326,
        "obv_trend": "rising",
        "price_change_pct": 0.14
      }
    },
    {
      "ticker": "XOM_US_EQ",
      "yf_symbol": "XOM",
      "action": "HOLD",
      "confidence": 0,
      "reasoning": "Model returned no decision",
      "was_executed": false,
      "rejection_reason": "Model error or no response",
      "indicators": {
        "symbol": "XOM",
        "current_price": 147.1750030517578,
        "volume": 69633,
        "rsi_14": 37.75,
        "macd": -0.7553,
        "macd_signal": -0.7042,
        "macd_histogram": -0.0511,
        "bb_upper": 150.1,
        "bb_middle": 148.16,
        "bb_lower": 146.23,
        "bb_pct": 0.244,
        "bb_width": 2.607,
        "ema_9": 147.57,
        "ema_21": 148.27,
        "ema_trend": "bearish",
        "atr_14": 0.918,
        "obv_trend": "falling",
        "price_change_pct": 0.06
      }
    },
    {
      "ticker": "JNJ_US_EQ",
      "yf_symbol": "JNJ",
      "action": "HOLD",
      "confidence": 0,
      "reasoning": "Model returned no decision",
      "was_executed": false,
      "rejection_reason": "Model error or no response",
      "indicators": {
        "symbol": "JNJ",
        "current_price": 240.75,
        "volume": 44177,
        "rsi_14": 60.0,
        "macd": 0.5037,
        "macd_signal": 0.4655,
        "macd_histogram": 0.0382,
        "bb_upper": 241.14,
        "bb_middle": 239.7,
        "bb_lower": 238.25,
        "bb_pct": 0.8649,
        "bb_width": 1.2052,
        "ema_9": 240.14,
        "ema_21": 239.71,
        "ema_trend": "bullish",
        "atr_14": 1.0013,
        "obv_trend": "rising",
        "price_change_pct": 0.08
      }
    },
    {
      "ticker": "WMT_US_EQ",
      "yf_symbol": "WMT",
      "action": "HOLD",
      "confidence": 0,
      "reasoning": "Model returned no decision",
      "was_executed": false,
      "rejection_reason": "Model error or no response",
      "indicators": {
        "symbol": "WMT",
        "current_price": 120.76000213623047,
        "volume": 93828,
        "rsi_14": 57.39,
        "macd": 0.0959,
        "macd_signal": 0.069,
        "macd_histogram": 0.0269,
        "bb_upper": 121.5,
        "bb_middle": 120.49,
        "bb_lower": 119.48,
        "bb_pct": 0.6338,
        "bb_width": 1.6726,
        "ema_9": 120.45,
        "ema_21": 120.36,
        "ema_trend": "bullish",
        "atr_14": 0.5787,
        "obv_trend": "rising",
        "price_change_pct": -0.02
      }
    }
  ]
}