{
  "run_time": "2026-06-08T19:39:07.851935+00:00",
  "decisions": [
    {
      "ticker": "AAPL_US_EQ",
      "yf_symbol": "AAPL",
      "action": "HOLD",
      "confidence": 0,
      "reasoning": "Model returned no decision",
      "was_executed": false,
      "rejection_reason": "Model error or no response",
      "indicators": {
        "symbol": "AAPL",
        "current_price": 302.94500732421875,
        "volume": 1491663,
        "rsi_14": 30.85,
        "macd": -1.8011,
        "macd_signal": -0.6349,
        "macd_histogram": -1.1662,
        "bb_upper": 317.83,
        "bb_middle": 310.12,
        "bb_lower": 302.41,
        "bb_pct": 0.0348,
        "bb_width": 4.9737,
        "ema_9": 307.02,
        "ema_21": 309.34,
        "ema_trend": "bearish",
        "atr_14": 2.6951,
        "obv_trend": "falling",
        "price_change_pct": 0.08
      }
    },
    {
      "ticker": "JPM_US_EQ",
      "yf_symbol": "JPM",
      "action": "HOLD",
      "confidence": 0,
      "reasoning": "Model returned no decision",
      "was_executed": false,
      "rejection_reason": "Model error or no response",
      "indicators": {
        "symbol": "JPM",
        "current_price": 311.5249938964844,
        "volume": 90613,
        "rsi_14": 51.22,
        "macd": 0.6472,
        "macd_signal": 1.0215,
        "macd_histogram": -0.3743,
        "bb_upper": 313.42,
        "bb_middle": 312.25,
        "bb_lower": 311.08,
        "bb_pct": 0.1895,
        "bb_width": 0.7486,
        "ema_9": 312.02,
        "ema_21": 311.76,
        "ema_trend": "bullish",
        "atr_14": 1.3518,
        "obv_trend": "falling",
        "price_change_pct": 0.1
      }
    },
    {
      "ticker": "XOM_US_EQ",
      "yf_symbol": "XOM",
      "action": "HOLD",
      "confidence": 0,
      "reasoning": "Model returned no decision",
      "was_executed": false,
      "rejection_reason": "Model error or no response",
      "indicators": {
        "symbol": "XOM",
        "current_price": 151.7949981689453,
        "volume": 209620,
        "rsi_14": 52.14,
        "macd": 0.0486,
        "macd_signal": -0.0161,
        "macd_histogram": 0.0647,
        "bb_upper": 153.05,
        "bb_middle": 151.32,
        "bb_lower": 149.6,
        "bb_pct": 0.636,
        "bb_width": 2.2858,
        "ema_9": 151.62,
        "ema_21": 151.54,
        "ema_trend": "bullish",
        "atr_14": 0.745,
        "obv_trend": "rising",
        "price_change_pct": 0.24
      }
    },
    {
      "ticker": "JNJ_US_EQ",
      "yf_symbol": "JNJ",
      "action": "HOLD",
      "confidence": 0,
      "reasoning": "Model returned no decision",
      "was_executed": false,
      "rejection_reason": "Model error or no response",
      "indicators": {
        "symbol": "JNJ",
        "current_price": 232.17999267578125,
        "volume": 189102,
        "rsi_14": 57.75,
        "macd": 0.4243,
        "macd_signal": 0.7642,
        "macd_histogram": -0.34,
        "bb_upper": 234.83,
        "bb_middle": 232.57,
        "bb_lower": 230.3,
        "bb_pct": 0.4147,
        "bb_width": 1.9499,
        "ema_9": 231.77,
        "ema_21": 231.68,
        "ema_trend": "bullish",
        "atr_14": 0.9338,
        "obv_trend": "rising",
        "price_change_pct": 0.2
      }
    },
    {
      "ticker": "WMT_US_EQ",
      "yf_symbol": "WMT",
      "action": "HOLD",
      "confidence": 0,
      "reasoning": "Model returned no decision",
      "was_executed": false,
      "rejection_reason": "Model error or no response",
      "indicators": {
        "symbol": "WMT",
        "current_price": 120.00499725341797,
        "volume": 302691,
        "rsi_14": 57.91,
        "macd": 0.3392,
        "macd_signal": 0.4236,
        "macd_histogram": -0.0844,
        "bb_upper": 120.47,
        "bb_middle": 119.82,
        "bb_lower": 119.17,
        "bb_pct": 0.6447,
        "bb_width": 1.0865,
        "ema_9": 119.83,
        "ema_21": 119.61,
        "ema_trend": "bullish",
        "atr_14": 0.5531,
        "obv_trend": "rising",
        "price_change_pct": 0.02
      }
    }
  ]
}