{
  "run_time": "2026-04-08T19:46:45.223314+00:00",
  "decisions": [
    {
      "ticker": "AAPL_US_EQ",
      "yf_symbol": "AAPL",
      "action": "HOLD",
      "confidence": 0,
      "reasoning": "Model returned no decision",
      "was_executed": false,
      "rejection_reason": "Model error or no response",
      "indicators": {
        "symbol": "AAPL",
        "current_price": 258.05999755859375,
        "volume": 1110627,
        "rsi_14": 58.68,
        "macd": 0.9881,
        "macd_signal": 0.7731,
        "macd_histogram": 0.215,
        "bb_upper": 261.82,
        "bb_middle": 255.61,
        "bb_lower": 249.39,
        "bb_pct": 0.6975,
        "bb_width": 4.8614,
        "ema_9": 257.33,
        "ema_21": 256.27,
        "ema_trend": "bullish",
        "atr_14": 1.4954,
        "obv_trend": "rising",
        "price_change_pct": 0.33
      }
    },
    {
      "ticker": "JPM_US_EQ",
      "yf_symbol": "JPM",
      "action": "HOLD",
      "confidence": 0,
      "reasoning": "Model returned no decision",
      "was_executed": false,
      "rejection_reason": "Model error or no response",
      "indicators": {
        "symbol": "JPM",
        "current_price": 307.760009765625,
        "volume": 312185,
        "rsi_14": 72.7,
        "macd": 2.9096,
        "macd_signal": 2.7804,
        "macd_histogram": 0.1292,
        "bb_upper": 313.31,
        "bb_middle": 303.31,
        "bb_lower": 293.32,
        "bb_pct": 0.7225,
        "bb_width": 6.5894,
        "ema_9": 306.56,
        "ema_21": 303.86,
        "ema_trend": "bullish",
        "atr_14": 1.6337,
        "obv_trend": "rising",
        "price_change_pct": 0.26
      }
    },
    {
      "ticker": "XOM_US_EQ",
      "yf_symbol": "XOM",
      "action": "HOLD",
      "confidence": 0,
      "reasoning": "Model returned no decision",
      "was_executed": false,
      "rejection_reason": "Model error or no response",
      "indicators": {
        "symbol": "XOM",
        "current_price": 155.25999450683594,
        "volume": 913285,
        "rsi_14": 39.39,
        "macd": -1.9642,
        "macd_signal": -1.9632,
        "macd_histogram": -0.001,
        "bb_upper": 165.52,
        "bb_middle": 157.39,
        "bb_lower": 149.25,
        "bb_pct": 0.3692,
        "bb_width": 10.3369,
        "ema_9": 155.2,
        "ema_21": 156.99,
        "ema_trend": "bearish",
        "atr_14": 1.4487,
        "obv_trend": "falling",
        "price_change_pct": -0.4
      }
    },
    {
      "ticker": "JNJ_US_EQ",
      "yf_symbol": "JNJ",
      "action": "HOLD",
      "confidence": 0,
      "reasoning": "Model returned no decision",
      "was_executed": false,
      "rejection_reason": "Model error or no response",
      "indicators": {
        "symbol": "JNJ",
        "current_price": 240.67999267578125,
        "volume": 267864,
        "rsi_14": 58.5,
        "macd": 0.0233,
        "macd_signal": -0.3922,
        "macd_histogram": 0.4155,
        "bb_upper": 241.14,
        "bb_middle": 238.92,
        "bb_lower": 236.71,
        "bb_pct": 0.8958,
        "bb_width": 1.8569,
        "ema_9": 239.86,
        "ema_21": 239.54,
        "ema_trend": "bullish",
        "atr_14": 1.0086,
        "obv_trend": "rising",
        "price_change_pct": 0.05
      }
    },
    {
      "ticker": "WMT_US_EQ",
      "yf_symbol": "WMT",
      "action": "HOLD",
      "confidence": 0,
      "reasoning": "Model returned no decision",
      "was_executed": false,
      "rejection_reason": "Model error or no response",
      "indicators": {
        "symbol": "WMT",
        "current_price": 126.96499633789062,
        "volume": 554987,
        "rsi_14": 68.18,
        "macd": 0.5757,
        "macd_signal": 0.2648,
        "macd_histogram": 0.3109,
        "bb_upper": 127.89,
        "bb_middle": 124.7,
        "bb_lower": 121.52,
        "bb_pct": 0.8551,
        "bb_width": 5.1055,
        "ema_9": 126.11,
        "ema_21": 125.39,
        "ema_trend": "bullish",
        "atr_14": 0.6286,
        "obv_trend": "rising",
        "price_change_pct": 0.26
      }
    }
  ]
}