{
  "run_time": "2026-03-09T18:06:48.099416+00:00",
  "decisions": [
    {
      "ticker": "AAPL_US_EQ",
      "yf_symbol": "AAPL",
      "action": "HOLD",
      "confidence": 0,
      "reasoning": "Model returned no decision",
      "was_executed": false,
      "rejection_reason": "Model error or no response",
      "indicators": {
        "symbol": "AAPL",
        "current_price": 256.489990234375,
        "volume": 658161,
        "rsi_14": 43.28,
        "macd": -0.5971,
        "macd_signal": -0.7224,
        "macd_histogram": 0.1254,
        "bb_upper": 258.12,
        "bb_middle": 256.88,
        "bb_lower": 255.63,
        "bb_pct": 0.3447,
        "bb_width": 0.9711,
        "ema_9": 256.85,
        "ema_21": 257.26,
        "ema_trend": "bearish",
        "atr_14": 1.3568,
        "obv_trend": "rising",
        "price_change_pct": 0.14
      }
    },
    {
      "ticker": "JPM_US_EQ",
      "yf_symbol": "JPM",
      "action": "HOLD",
      "confidence": 0,
      "reasoning": "Model returned no decision",
      "was_executed": false,
      "rejection_reason": "Model error or no response",
      "indicators": {
        "symbol": "JPM",
        "current_price": 285.6499938964844,
        "volume": 87435,
        "rsi_14": 43.47,
        "macd": -1.8477,
        "macd_signal": -2.2358,
        "macd_histogram": 0.3882,
        "bb_upper": 290.11,
        "bb_middle": 285.81,
        "bb_lower": 281.51,
        "bb_pct": 0.4813,
        "bb_width": 3.007,
        "ema_9": 285.11,
        "ema_21": 286.48,
        "ema_trend": "bearish",
        "atr_14": 1.8535,
        "obv_trend": "rising",
        "price_change_pct": 0.1
      }
    },
    {
      "ticker": "XOM_US_EQ",
      "yf_symbol": "XOM",
      "action": "HOLD",
      "confidence": 0,
      "reasoning": "Model returned no decision",
      "was_executed": false,
      "rejection_reason": "Model error or no response",
      "indicators": {
        "symbol": "XOM",
        "current_price": 151.41029357910156,
        "volume": 142474,
        "rsi_14": 48.98,
        "macd": 0.2056,
        "macd_signal": 0.3284,
        "macd_histogram": -0.1228,
        "bb_upper": 153.0,
        "bb_middle": 151.84,
        "bb_lower": 150.68,
        "bb_pct": 0.3143,
        "bb_width": 1.529,
        "ema_9": 151.75,
        "ema_21": 151.64,
        "ema_trend": "bullish",
        "atr_14": 1.0787,
        "obv_trend": "falling",
        "price_change_pct": -0.31
      }
    },
    {
      "ticker": "JNJ_US_EQ",
      "yf_symbol": "JNJ",
      "action": "HOLD",
      "confidence": 0,
      "reasoning": "Model returned no decision",
      "was_executed": false,
      "rejection_reason": "Model error or no response",
      "indicators": {
        "symbol": "JNJ",
        "current_price": 241.4149932861328,
        "volume": 78689,
        "rsi_14": 54.38,
        "macd": 0.6558,
        "macd_signal": 0.3825,
        "macd_histogram": 0.2733,
        "bb_upper": 244.1,
        "bb_middle": 240.19,
        "bb_lower": 236.28,
        "bb_pct": 0.6562,
        "bb_width": 3.2569,
        "ema_9": 241.6,
        "ema_21": 240.77,
        "ema_trend": "bullish",
        "atr_14": 1.0854,
        "obv_trend": "falling",
        "price_change_pct": -0.01
      }
    },
    {
      "ticker": "WMT_US_EQ",
      "yf_symbol": "WMT",
      "action": "HOLD",
      "confidence": 0,
      "reasoning": "Model returned no decision",
      "was_executed": false,
      "rejection_reason": "Model error or no response",
      "indicators": {
        "symbol": "WMT",
        "current_price": 123.16000366210938,
        "volume": 102891,
        "rsi_14": 45.91,
        "macd": -0.2358,
        "macd_signal": -0.3003,
        "macd_histogram": 0.0645,
        "bb_upper": 123.95,
        "bb_middle": 123.32,
        "bb_lower": 122.69,
        "bb_pct": 0.3751,
        "bb_width": 1.0239,
        "ema_9": 123.22,
        "ema_21": 123.36,
        "ema_trend": "bearish",
        "atr_14": 0.6486,
        "obv_trend": "falling",
        "price_change_pct": 0.14
      }
    }
  ]
}