{
  "run_time": "2026-06-22T23:01:31.557217+00:00",
  "decisions": [
    {
      "ticker": "AAPL_US_EQ",
      "yf_symbol": "AAPL",
      "action": "HOLD",
      "confidence": 0,
      "reasoning": "Model returned no decision",
      "was_executed": false,
      "rejection_reason": "Model error or no response",
      "indicators": {
        "symbol": "AAPL",
        "current_price": 296.7900085449219,
        "volume": 6099091,
        "rsi_14": 40.01,
        "macd": 0.1767,
        "macd_signal": 0.4535,
        "macd_histogram": -0.2768,
        "bb_upper": 301.89,
        "bb_middle": 298.98,
        "bb_lower": 296.07,
        "bb_pct": 0.1239,
        "bb_width": 1.947,
        "ema_9": 298.86,
        "ema_21": 298.87,
        "ema_trend": "bearish",
        "atr_14": 1.3418,
        "obv_trend": "falling",
        "price_change_pct": -0.76
      }
    },
    {
      "ticker": "JPM_US_EQ",
      "yf_symbol": "JPM",
      "action": "HOLD",
      "confidence": 0,
      "reasoning": "Model returned no decision",
      "was_executed": false,
      "rejection_reason": "Model error or no response",
      "indicators": {
        "symbol": "JPM",
        "current_price": 331.8500061035156,
        "volume": 1299057,
        "rsi_14": 54.92,
        "macd": 0.3466,
        "macd_signal": 0.0504,
        "macd_histogram": 0.2963,
        "bb_upper": 333.97,
        "bb_middle": 329.95,
        "bb_lower": 325.92,
        "bb_pct": 0.7368,
        "bb_width": 2.4376,
        "ema_9": 331.48,
        "ema_21": 331.01,
        "ema_trend": "bullish",
        "atr_14": 1.5751,
        "obv_trend": "falling",
        "price_change_pct": -0.14
      }
    },
    {
      "ticker": "XOM_US_EQ",
      "yf_symbol": "XOM",
      "action": "HOLD",
      "confidence": 0,
      "reasoning": "Model returned no decision",
      "was_executed": false,
      "rejection_reason": "Model error or no response",
      "indicators": {
        "symbol": "XOM",
        "current_price": 138.4600067138672,
        "volume": 2960292,
        "rsi_14": 50.56,
        "macd": -0.1092,
        "macd_signal": -0.308,
        "macd_histogram": 0.1987,
        "bb_upper": 138.96,
        "bb_middle": 137.9,
        "bb_lower": 136.85,
        "bb_pct": 0.7635,
        "bb_width": 1.5286,
        "ema_9": 138.35,
        "ema_21": 138.3,
        "ema_trend": "bullish",
        "atr_14": 0.7138,
        "obv_trend": "falling",
        "price_change_pct": -0.24
      }
    },
    {
      "ticker": "JNJ_US_EQ",
      "yf_symbol": "JNJ",
      "action": "HOLD",
      "confidence": 0,
      "reasoning": "Model returned no decision",
      "was_executed": false,
      "rejection_reason": "Model error or no response",
      "indicators": {
        "symbol": "JNJ",
        "current_price": 231.27000427246094,
        "volume": 1043724,
        "rsi_14": 54.56,
        "macd": -0.0861,
        "macd_signal": -0.3504,
        "macd_histogram": 0.2644,
        "bb_upper": 232.03,
        "bb_middle": 230.05,
        "bb_lower": 228.08,
        "bb_pct": 0.8085,
        "bb_width": 1.7156,
        "ema_9": 230.71,
        "ema_21": 230.57,
        "ema_trend": "bullish",
        "atr_14": 1.0281,
        "obv_trend": "rising",
        "price_change_pct": 0.29
      }
    },
    {
      "ticker": "WMT_US_EQ",
      "yf_symbol": "WMT",
      "action": "HOLD",
      "confidence": 0,
      "reasoning": "Model returned no decision",
      "was_executed": false,
      "rejection_reason": "Model error or no response",
      "indicators": {
        "symbol": "WMT",
        "current_price": 117.12000274658203,
        "volume": 2153555,
        "rsi_14": 37.77,
        "macd": -0.295,
        "macd_signal": -0.3458,
        "macd_histogram": 0.0508,
        "bb_upper": 117.82,
        "bb_middle": 117.34,
        "bb_lower": 116.85,
        "bb_pct": 0.2753,
        "bb_width": 0.8203,
        "ema_9": 117.28,
        "ema_21": 117.49,
        "ema_trend": "bearish",
        "atr_14": 0.4438,
        "obv_trend": "falling",
        "price_change_pct": -0.06
      }
    }
  ]
}