{
  "run_time": "2026-05-27T19:36:25.101604+00:00",
  "decisions": [
    {
      "ticker": "AAPL_US_EQ",
      "yf_symbol": "AAPL",
      "action": "HOLD",
      "confidence": 0,
      "reasoning": "Model returned no decision",
      "was_executed": false,
      "rejection_reason": "Model error or no response",
      "indicators": {
        "symbol": "AAPL",
        "current_price": 309.9549865722656,
        "volume": 425695,
        "rsi_14": 49.4,
        "macd": 0.4185,
        "macd_signal": 0.699,
        "macd_histogram": -0.2805,
        "bb_upper": 312.78,
        "bb_middle": 310.45,
        "bb_lower": 308.11,
        "bb_pct": 0.3948,
        "bb_width": 1.502,
        "ema_9": 310.48,
        "ema_21": 310.33,
        "ema_trend": "bullish",
        "atr_14": 1.1248,
        "obv_trend": "falling",
        "price_change_pct": 0.04
      }
    },
    {
      "ticker": "JPM_US_EQ",
      "yf_symbol": "JPM",
      "action": "HOLD",
      "confidence": 0,
      "reasoning": "Model returned no decision",
      "was_executed": false,
      "rejection_reason": "Model error or no response",
      "indicators": {
        "symbol": "JPM",
        "current_price": 298.92999267578125,
        "volume": 76528,
        "rsi_14": 41.53,
        "macd": -1.7799,
        "macd_signal": -1.6589,
        "macd_histogram": -0.121,
        "bb_upper": 308.86,
        "bb_middle": 301.25,
        "bb_lower": 293.64,
        "bb_pct": 0.3478,
        "bb_width": 5.0531,
        "ema_9": 299.02,
        "ema_21": 300.75,
        "ema_trend": "bearish",
        "atr_14": 1.681,
        "obv_trend": "falling",
        "price_change_pct": -0.05
      }
    },
    {
      "ticker": "XOM_US_EQ",
      "yf_symbol": "XOM",
      "action": "HOLD",
      "confidence": 0,
      "reasoning": "Model returned no decision",
      "was_executed": false,
      "rejection_reason": "Model error or no response",
      "indicators": {
        "symbol": "XOM",
        "current_price": 147.99000549316406,
        "volume": 153444,
        "rsi_14": 33.3,
        "macd": -1.2567,
        "macd_signal": -1.4847,
        "macd_histogram": 0.228,
        "bb_upper": 151.05,
        "bb_middle": 148.75,
        "bb_lower": 146.45,
        "bb_pct": 0.3342,
        "bb_width": 3.0898,
        "ema_9": 148.26,
        "ema_21": 149.19,
        "ema_trend": "bearish",
        "atr_14": 0.8191,
        "obv_trend": "rising",
        "price_change_pct": -0.29
      }
    },
    {
      "ticker": "JNJ_US_EQ",
      "yf_symbol": "JNJ",
      "action": "HOLD",
      "confidence": 0,
      "reasoning": "Model returned no decision",
      "was_executed": false,
      "rejection_reason": "Model error or no response",
      "indicators": {
        "symbol": "JNJ",
        "current_price": 231.9600067138672,
        "volume": 55000,
        "rsi_14": 52.06,
        "macd": 0.0601,
        "macd_signal": 0.0053,
        "macd_histogram": 0.0549,
        "bb_upper": 232.92,
        "bb_middle": 231.54,
        "bb_lower": 230.16,
        "bb_pct": 0.6518,
        "bb_width": 1.1931,
        "ema_9": 231.88,
        "ema_21": 231.79,
        "ema_trend": "bullish",
        "atr_14": 0.774,
        "obv_trend": "rising",
        "price_change_pct": -0.07
      }
    },
    {
      "ticker": "WMT_US_EQ",
      "yf_symbol": "WMT",
      "action": "HOLD",
      "confidence": 0,
      "reasoning": "Model returned no decision",
      "was_executed": false,
      "rejection_reason": "Model error or no response",
      "indicators": {
        "symbol": "WMT",
        "current_price": 118.68009948730469,
        "volume": 197257,
        "rsi_14": 40.72,
        "macd": -0.3905,
        "macd_signal": -0.5609,
        "macd_histogram": 0.1704,
        "bb_upper": 119.07,
        "bb_middle": 118.58,
        "bb_lower": 118.08,
        "bb_pct": 0.6058,
        "bb_width": 0.8318,
        "ema_9": 118.71,
        "ema_21": 118.89,
        "ema_trend": "bearish",
        "atr_14": 0.5052,
        "obv_trend": "falling",
        "price_change_pct": 0.03
      }
    }
  ]
}